<?xml version="1.0" encoding="utf-8"?><CommandBatchResponse xmlns:xsi="http://www.w3.org/2001/XMLSchema-instance" xmlns:xsd="http://www.w3.org/2001/XMLSchema" xmlns="http://schemas.remotex.net/Apps/201207/Commands"><Href>commands</Href><Id>Create Case demo</Id><HasErrors>true</HasErrors><Received>2012-08-27T14:46:18.9594685Z</Received><CommandResponse><ErrorMessage>Invalid resource ID or display name: abcdefg</ErrorMessage><HasErrors>true</HasErrors><Command><Name>CreateCase</Name><Parameter><Name>Title</Name><Value>Case title</Value></Parameter><Parameter><Name>Description</Name><Value>Case which wont be created due to invalid resource ID</Value></Parameter><Parameter><Name>WorkorderResource</Name><Value>abcdefg</Value></Parameter></Command></CommandResponse></CommandBatchResponse>